PyMachina/__init__.py
PyMachina/core.py
pymachina-1.0.0.dist-info/licenses/LICENSE
pymachina-1.0.0.dist-info/METADATA
pymachina-1.0.0.dist-info/WHEEL
pymachina-1.0.0.dist-info/top_level.txt
pymachina-1.0.0.dist-info/RECORD
