Metadata-Version: 2.4
Name: PyMachina
Version: 1.0.0
Summary: A binary inspection and visualization tool for EXE, BIN, HEX, and Arduino files.
Home-page: https://github.com/EdenGithhub/PyMachina
Author: Eden Simamora
Author-email: Eden Simamora <aeden6877@gmail.com>
License: MIT
Keywords: binary,hex,arduino,reverse engineering,visualization
Requires-Python: >=3.7
License-File: LICENSE
Requires-Dist: numpy
Requires-Dist: matplotlib
Requires-Dist: colorama
Requires-Dist: pyfiglet
Requires-Dist: hexdump
Requires-Dist: rich
Requires-Dist: click
Requires-Dist: tqdm
Requires-Dist: Pillow
Dynamic: author
Dynamic: home-page
Dynamic: license-file
Dynamic: requires-python
